strcompare.cp38-win_amd64.pyd
strcompare-2.0.1.dist-info/LICENSE.txt
strcompare-2.0.1.dist-info/METADATA
strcompare-2.0.1.dist-info/WHEEL
strcompare-2.0.1.dist-info/top_level.txt
strcompare-2.0.1.dist-info/RECORD
