Metadata-Version: 2.1
Name: strcompare
Version: 2.0.1
Summary: Methods to assess string similarity.
Home-page: https://github.com/The-Slick-Nick/string-compare
Author: Slick Nick
Author-email: nfeezor@gmail.com
License-File: LICENSE.txt
